{"6a0d42a5-05ca-48bd-9925-1af0b801030a":{"id":"6a0d42a5-05ca-48bd-9925-1af0b801030a","name":"Jeans","description":"White","price":29.99,"minimumQuantity":10,"maximumQuantity":50,"category":"Electronics","supplier":"Best Supplier","createdOn":"2024-03-11T20:10:18.201377"},"33b177a4-2c1c-43ce-999c-eed68a7867dc":{"id":"33b177a4-2c1c-43ce-999c-eed68a7867dc","name":"Jeans","description":"Red","price":29.99,"minimumQuantity":10,"maximumQuantity":50,"category":"Electronics","supplier":"Best Supplier","createdOn":"2024-03-11T20:10:18.201733"}}